skyrelis/__init__.py
skyrelis/decorators.py
skyrelis/config/__init__.py
skyrelis/config/observer_config.py
skyrelis/core/__init__.py
skyrelis/core/agent_observer.py
skyrelis/core/monitored_agent.py
skyrelis/core/framework_adapters/__init__.py
skyrelis/core/framework_adapters/base_adapter.py
skyrelis/core/framework_adapters/crewai_adapter.py
skyrelis/core/framework_adapters/framework_registry.py
skyrelis/core/framework_adapters/langchain_adapter.py
skyrelis/core/framework_adapters/opentelemetry_integration.py
skyrelis/opentelemetry_instrumentation_crewai/.flake8
skyrelis/opentelemetry_instrumentation_crewai/README.md
skyrelis/opentelemetry_instrumentation_crewai/poetry.lock
skyrelis/opentelemetry_instrumentation_crewai/poetry.toml
skyrelis/opentelemetry_instrumentation_crewai/pyproject.toml
skyrelis/opentelemetry_instrumentation_crewai/opentelemetry/instrumentation/crewai/__init__.py
skyrelis/opentelemetry_instrumentation_crewai/opentelemetry/instrumentation/crewai/crewai_span_attributes.py
skyrelis/opentelemetry_instrumentation_crewai/opentelemetry/instrumentation/crewai/instrumentation.py
skyrelis/opentelemetry_instrumentation_crewai/opentelemetry/instrumentation/crewai/version.py
skyrelis/utils/__init__.py
skyrelis/utils/langsmith_integration.py
skyrelis/utils/opentelemetry_integration.py
skyrelis/utils/remote_observer_client.py
skyrelis-0.1.5.dist-info/licenses/LICENSE
skyrelis-0.1.5.dist-info/METADATA
skyrelis-0.1.5.dist-info/WHEEL
skyrelis-0.1.5.dist-info/entry_points.txt
skyrelis-0.1.5.dist-info/top_level.txt
skyrelis-0.1.5.dist-info/RECORD
