Metadata-Version: 2.4
Name: skyrelis
Version: 0.1.5
Summary: AI Agent Security Library - Enterprise-grade security for AI agents, starting with comprehensive observability across multiple frameworks
Home-page: https://github.com/skyrelis/skyrelis
Author: Skyrelis Security Team
Author-email: Skyrelis Security Team <security@skyrelis.com>
Maintainer-email: Skyrelis Security Team <security@skyrelis.com>
License: Proprietary
Project-URL: Homepage, https://github.com/skyrelis/skyrelis
Project-URL: Documentation, https://skyrelis.readthedocs.io
Project-URL: Repository, https://github.com/skyrelis/skyrelis
Project-URL: Bug Reports, https://github.com/skyrelis/skyrelis/issues
Project-URL: Security, https://github.com/skyrelis/skyrelis/security
Project-URL: Funding, https://github.com/sponsors/skyrelis
Keywords: ai,agents,security,observability,monitoring,tracing,langchain,telemetry,analytics,debugging,performance,opentelemetry,compliance,audit,threat-detection,cybersecurity,enterprise,SOC2,GDPR,HIPAA,risk-management,governance
Classifier: Development Status :: 4 - Beta
Classifier: Intended Audience :: Developers
Classifier: Intended Audience :: System Administrators
Classifier: Intended Audience :: Information Technology
Classifier: License :: Other/Proprietary License
Classifier: Operating System :: OS Independent
Classifier: Programming Language :: Python :: 3
Classifier: Programming Language :: Python :: 3.8
Classifier: Programming Language :: Python :: 3.9
Classifier: Programming Language :: Python :: 3.10
Classifier: Programming Language :: Python :: 3.11
Classifier: Programming Language :: Python :: 3.12
Classifier: Topic :: Software Development :: Libraries :: Python Modules
Classifier: Topic :: System :: Monitoring
Classifier: Topic :: Security
Classifier: Topic :: Security :: Cryptography
Classifier: Topic :: System :: Logging
Classifier: Topic :: Scientific/Engineering :: Artificial Intelligence
Classifier: Topic :: Office/Business :: Financial
Classifier: Framework :: AsyncIO
Classifier: Environment :: Web Environment
Requires-Python: >=3.8
License-File: LICENSE
Requires-Dist: langchain>=0.1.0
Requires-Dist: langchain-core>=0.1.0
Requires-Dist: langchain-openai>=0.0.5
Requires-Dist: requests>=2.25.0
Requires-Dist: aiohttp>=3.8.0
Requires-Dist: pydantic>=1.8.0
Requires-Dist: python-dotenv>=0.19.0
Provides-Extra: security
Requires-Dist: cryptography>=3.4.0; extra == "security"
Requires-Dist: bcrypt>=3.2.0; extra == "security"
Requires-Dist: pyjwt>=2.0.0; extra == "security"
Provides-Extra: opentelemetry
Requires-Dist: opentelemetry-api>=1.0.0; extra == "opentelemetry"
Requires-Dist: opentelemetry-sdk>=1.0.0; extra == "opentelemetry"
Requires-Dist: opentelemetry-instrumentation>=0.30b0; extra == "opentelemetry"
Requires-Dist: opentelemetry-exporter-jaeger>=1.0.0; extra == "opentelemetry"
Provides-Extra: langsmith
Requires-Dist: langsmith>=0.0.30; extra == "langsmith"
Provides-Extra: crewai
Requires-Dist: crewai>=0.70.0; extra == "crewai"
Requires-Dist: opentelemetry-api>=1.21.0; extra == "crewai"
Requires-Dist: opentelemetry-sdk>=1.21.0; extra == "crewai"
Provides-Extra: compliance
Requires-Dist: psycopg2-binary>=2.9.0; extra == "compliance"
Requires-Dist: sqlalchemy>=1.4.0; extra == "compliance"
Provides-Extra: threat-detection
Requires-Dist: scikit-learn>=1.0.0; extra == "threat-detection"
Requires-Dist: pandas>=1.3.0; extra == "threat-detection"
Requires-Dist: numpy>=1.21.0; extra == "threat-detection"
Provides-Extra: dev
Requires-Dist: pytest>=7.0.0; extra == "dev"
Requires-Dist: pytest-asyncio>=0.21.0; extra == "dev"
Requires-Dist: black>=22.0.0; extra == "dev"
Requires-Dist: flake8>=4.0.0; extra == "dev"
Requires-Dist: mypy>=0.991; extra == "dev"
Requires-Dist: bandit>=1.7.0; extra == "dev"
Provides-Extra: all
Requires-Dist: cryptography>=3.4.0; extra == "all"
Requires-Dist: bcrypt>=3.2.0; extra == "all"
Requires-Dist: pyjwt>=2.0.0; extra == "all"
Requires-Dist: opentelemetry-api>=1.0.0; extra == "all"
Requires-Dist: opentelemetry-sdk>=1.0.0; extra == "all"
Requires-Dist: opentelemetry-instrumentation>=0.30b0; extra == "all"
Requires-Dist: opentelemetry-exporter-jaeger>=1.0.0; extra == "all"
Requires-Dist: langsmith>=0.0.30; extra == "all"
Requires-Dist: psycopg2-binary>=2.9.0; extra == "all"
Requires-Dist: sqlalchemy>=1.4.0; extra == "all"
Requires-Dist: scikit-learn>=1.0.0; extra == "all"
Requires-Dist: pandas>=1.3.0; extra == "all"
Requires-Dist: numpy>=1.21.0; extra == "all"
Dynamic: author
Dynamic: home-page
Dynamic: license-file
Dynamic: requires-python
